smartplot/__init__.py
smartplot/smartplot.py
smartplot-0.1.2.dist-info/METADATA
smartplot-0.1.2.dist-info/WHEEL
smartplot-0.1.2.dist-info/top_level.txt
smartplot-0.1.2.dist-info/RECORD
